{"page":0,"full_page":false,"headline":"Detenido en Guadalajara un marroquí por incitar en las redes a cometer atentados suicidas","date":"2018-05-04T14:20:12.797Z","content":"Detenido en Guadalajara un marroquí por incitar en las redes a cometer atentados suicidas\n\nLos agentes han incautado al arrestado numerosos medios electrónicos y terminales telefónicos\nDivulgaba propaganda de Daesh y Al Qaeda\nLa Policía ha detenido en Guadalajara a un hombre de nacionalidad marroquí por incitar en las redes sociales a cometer atentados suicidas y por enaltecimiento del terrorismo yihadista, según ha informado el Ministerio del Interior.\nHan sido agentes de la Brigada Provincial de Información de Madrid, en colaboración con la de Guadalajara y coordinados por la Comisaría General de Información, quienes han arrestado a este hombre, que estaba \"fuertemente radicalizado\".\nAsí, utilizaba las redes sociales para divulgar propaganda de las organizaciones terroristas Daesh y Al Qaeda, según la Policía, que le ha incautado numerosos medios electrónicos, terminales telefónicos y documentación de gran interés que están siendo analizados por los investigadores.\nHaber consentido la entrada en España de población musulmana ha sido uno de los errores más graves de los últimos 500 años. Gracias, casta. No olvidaremos.\n© ELMUNDO.es Avenida de San Luis 25 - 28033 MADRID Una web de Unidad Editorial\nSíguenos en","url":"https://www.elmundo.es/espana/2018/04/30/5ae6ef2de2704e764c8b45b6.html","newspaper":"elmundo","scraper_id":"all-digitalocean-scraper","id":"1567a41f-54f7-4ca2-42d8-5d7c02cb4ee2","sentiment_analysis":{"score":-6,"comparative":-0.03,"tokens":[{"value":"detenido","negate":false},{"value":"en","negate":false},{"value":"guadalajara","negate":false},{"value":"un","negate":false},{"value":"marroquí","negate":false},{"value":"por","negate":false},{"value":"incitar","negate":false},{"value":"en","negate":false},{"value":"las","negate":false},{"value":"redes","negate":false},{"value":"a","negate":false},{"value":"cometer","negate":false},{"value":"atentados","negate":false},{"value":"suicidas","negate":false},{"value":"los","negate":false},{"value":"agentes","negate":false},{"value":"han","negate":false},{"value":"incautado","negate":false},{"value":"al","negate":false},{"value":"arrestado","negate":false},{"value":"numerosos","negate":false},{"value":"medios","negate":false},{"value":"electrónicos","negate":false},{"value":"y","negate":false},{"value":"terminales","negate":false},{"value":"telefónicos","negate":false},{"value":"divulgaba","negate":false},{"value":"propaganda","negate":false},{"value":"de","negate":false},{"value":"daesh","negate":false},{"value":"y","negate":false},{"value":"al","negate":false},{"value":"qaeda","negate":false},{"value":"la","negate":false},{"value":"policía","negate":false},{"value":"ha","negate":false},{"value":"detenido","negate":false},{"value":"en","negate":false},{"value":"guadalajara","negate":false},{"value":"a","negate":false},{"value":"un","negate":false},{"value":"hombre","negate":false},{"value":"de","negate":false},{"value":"nacionalidad","negate":false},{"value":"marroquí","negate":false},{"value":"por","negate":false},{"value":"incitar","negate":false},{"value":"en","negate":false},{"value":"las","negate":false},{"value":"redes","negate":false},{"value":"sociales","negate":false},{"value":"a","negate":false},{"value":"cometer","negate":false},{"value":"atentados","negate":false},{"value":"suicidas","negate":false},{"value":"y","negate":false},{"value":"por","negate":false},{"value":"enaltecimiento","negate":false},{"value":"del","negate":false},{"value":"terrorismo","negate":false},{"value":"yihadista","negate":false},{"value":"según","negate":false},{"value":"ha","negate":false},{"value":"informado","negate":false},{"value":"el","negate":false},{"value":"ministerio","negate":false},{"value":"del","negate":false},{"value":"interior","negate":false},{"value":"han","negate":false},{"value":"sido","negate":false},{"value":"agentes","negate":false},{"value":"de","negate":false},{"value":"la","negate":false},{"value":"brigada","negate":false},{"value":"provincial","negate":false},{"value":"de","negate":false},{"value":"información","negate":false},{"value":"de","negate":false},{"value":"madrid","negate":false},{"value":"en","negate":false},{"value":"colaboración","negate":false},{"value":"con","negate":false},{"value":"la","negate":false},{"value":"de","negate":false},{"value":"guadalajara","negate":false},{"value":"y","negate":false},{"value":"coordinados","negate":false},{"value":"por","negate":false},{"value":"la","negate":false},{"value":"comisaría","negate":false},{"value":"general","negate":false},{"value":"de","negate":false},{"value":"información","negate":false},{"value":"quienes","negate":false},{"value":"han","negate":false},{"value":"arrestado","negate":false},{"value":"a","negate":false},{"value":"este","negate":false},{"value":"hombre","negate":false},{"value":"que","negate":false},{"value":"estaba","negate":false},{"value":"\"fuertemente","negate":false},{"value":"radicalizado\"","negate":false},{"value":"así","negate":false},{"value":"utilizaba","negate":false},{"value":"las","negate":false},{"value":"redes","negate":false},{"value":"sociales","negate":false},{"value":"para","negate":false},{"value":"divulgar","negate":false},{"value":"propaganda","negate":false},{"value":"de","negate":false},{"value":"las","negate":false},{"value":"organizaciones","negate":false},{"value":"terroristas","negate":false},{"value":"daesh","negate":false},{"value":"y","negate":false},{"value":"al","negate":false},{"value":"qaeda","negate":false},{"value":"según","negate":false},{"value":"la","negate":false},{"value":"policía","negate":false},{"value":"que","negate":false},{"value":"le","negate":false},{"value":"ha","negate":false},{"value":"incautado","negate":false},{"value":"numerosos","negate":false},{"value":"medios","negate":false},{"value":"electrónicos","negate":false},{"value":"terminales","negate":false},{"value":"telefónicos","negate":false},{"value":"y","negate":false},{"value":"documentación","negate":false},{"value":"de","negate":false},{"value":"gran","negate":false},{"value":"interés","negate":false},{"value":"que","negate":false},{"value":"están","negate":false},{"value":"siendo","negate":false},{"value":"analizados","negate":false},{"value":"por","negate":false},{"value":"los","negate":false},{"value":"investigadores","negate":false},{"value":"haber","negate":false},{"value":"consentido","negate":false},{"value":"la","negate":false},{"value":"entrada","negate":false},{"value":"en","negate":false},{"value":"españa","negate":false},{"value":"de","negate":false},{"value":"población","negate":false},{"value":"musulmana","negate":false},{"value":"ha","negate":false},{"value":"sido","negate":false},{"value":"uno","negate":false},{"value":"de","negate":false},{"value":"los","negate":false},{"value":"errores","negate":false},{"value":"más","negate":false},{"value":"graves","negate":false},{"value":"de","negate":false},{"value":"los","negate":false},{"value":"últimos","negate":false},{"value":"500","negate":false},{"value":"años","negate":false},{"value":"gracias","negate":false},{"value":"casta","negate":false},{"value":"no","negate":true},{"value":"olvidaremos","negate":false},{"value":"©","negate":false},{"value":"elmundo","negate":false},{"value":"es","negate":false},{"value":"avenida","negate":false},{"value":"de","negate":false},{"value":"san","negate":false},{"value":"luis","negate":false},{"value":"25","negate":false},{"value":"-","negate":false},{"value":"28033","negate":false},{"value":"madrid","negate":false},{"value":"una","negate":false},{"value":"web","negate":false},{"value":"de","negate":false},{"value":"unidad","negate":false},{"value":"editorial","negate":false},{"value":"síguenos","negate":false},{"value":"en","negate":false}],"words":["detenido","cometer","propaganda","detenido","cometer","propaganda","terroristas","errores","gracias"],"positive":["cometer","cometer","gracias"],"negative":["detenido","propaganda","detenido","propaganda","terroristas","errores"]}}