{"page":0,"full_page":false,"headline":"elmundo.es | Opinión","date":"2009-08-17T14:20:12.797Z","content":"elmundo.es | Opinión\n\nLíder mundial en español\nDomingo 16/08/2009. Actualizado 12:19h.\nEl tiempo en Madrid: Sol. 21°C de mánima y 35°C de máxima.\nEsta p�gina cambia sus contenidos todos los d�as a partir de las 11:00h.\nUn espectacular ataque suicida contra la OTAN en Kabul sacude la campa�a a cinco d�as de los comicios\nLos bomberos avisaron de deficiencias de seguridad tras el accidente de Spanair\nEl fin del sufrimiento de un chico de 16 a�os que quiere ser mujer\n\nLA TRONERA por ANTONIO GALA\nCONJETURAS por ERASMO\nTodos los columnistas »\n\n                                                15.08.2009 20:06 hrs\n                                            \n\n                                                El blog de Santiago Gonz�lez\n                                                de\n                                                \n                                                    \n                                                \n                                            \n\n                                                15.08.2009 18:01 hrs\n                                            \n\n                                                El Mundo por dentro\n                                                de\n                                                \n                                                    \n                                                \n                                            \n\n                                                10.08.2009 12:53 hrs\n                                            \n\n                                                Consejo Editorial\n                                                de\n                                                \n                                                    \n                                                \n                                            \n\n                                                31.07.2009 13:06 hrs\n                                            \n\n                                                dragolandia\n                                                de\n                                                \n                                                    \n                                                \n                                            \n\n                                                30.07.2009 14:06 hrs\n                                            \n\n                                                Palabras Archivadas\n                                                de\n                                                \n                                                    \n                                                \n                                            \n�Cree que ETA habr� desaparecido dentro de otros 50 a�os?\n\nEnvía tu carta\nAmpliar foto\n09.07.2009\n06.07.2009\n03.07.2009\n15.06.2009\nDevoto de Al Qaeda en Gaza \n\n \n\nAmpli� el Guggenheim de Nueva York \n\n \n","url":"https://www.elmundo.es/elmundo/hemeroteca/2009/08/17/m/opinion.html","newspaper":"elmundo","scraper_id":"all-digitalocean-scraper","id":"1266d210-5839-48b8-650c-6a5f0adab0e3","sentiment_analysis":{"score":-4,"comparative":-0.02,"tokens":[{"value":"elmundo","negate":false},{"value":"es","negate":false},{"value":"|","negate":false},{"value":"opinión","negate":false},{"value":"líder","negate":false},{"value":"mundial","negate":false},{"value":"en","negate":false},{"value":"español","negate":false},{"value":"domingo","negate":false},{"value":"16","negate":false},{"value":"08","negate":false},{"value":"2009","negate":false},{"value":"actualizado","negate":false},{"value":"12","negate":false},{"value":"19","negate":false},{"value":"h","negate":false},{"value":"el","negate":false},{"value":"tiempo","negate":false},{"value":"en","negate":false},{"value":"madrid","negate":false},{"value":"sol","negate":false},{"value":"21","negate":false},{"value":"°c","negate":false},{"value":"de","negate":false},{"value":"mánima","negate":false},{"value":"y","negate":false},{"value":"35","negate":false},{"value":"°c","negate":false},{"value":"de","negate":false},{"value":"máxima","negate":false},{"value":"esta","negate":false},{"value":"p�gina","negate":false},{"value":"cambia","negate":false},{"value":"sus","negate":false},{"value":"contenidos","negate":false},{"value":"todos","negate":false},{"value":"los","negate":false},{"value":"d�as","negate":false},{"value":"a","negate":false},{"value":"partir","negate":false},{"value":"de","negate":false},{"value":"las","negate":false},{"value":"11","negate":false},{"value":"00","negate":false},{"value":"h","negate":false},{"value":"un","negate":false},{"value":"espectacular","negate":false},{"value":"ataque","negate":false},{"value":"suicida","negate":false},{"value":"contra","negate":false},{"value":"la","negate":false},{"value":"otan","negate":false},{"value":"en","negate":false},{"value":"kabul","negate":false},{"value":"sacude","negate":false},{"value":"la","negate":false},{"value":"campa�a","negate":false},{"value":"a","negate":false},{"value":"cinco","negate":false},{"value":"d�as","negate":false},{"value":"de","negate":false},{"value":"los","negate":false},{"value":"comicios","negate":false},{"value":"los","negate":false},{"value":"bomberos","negate":false},{"value":"avisaron","negate":false},{"value":"de","negate":false},{"value":"deficiencias","negate":false},{"value":"de","negate":false},{"value":"seguridad","negate":false},{"value":"tras","negate":false},{"value":"el","negate":false},{"value":"accidente","negate":false},{"value":"de","negate":false},{"value":"spanair","negate":false},{"value":"el","negate":false},{"value":"fin","negate":false},{"value":"del","negate":false},{"value":"sufrimiento","negate":false},{"value":"de","negate":false},{"value":"un","negate":false},{"value":"chico","negate":false},{"value":"de","negate":false},{"value":"16","negate":false},{"value":"a�os","negate":false},{"value":"que","negate":false},{"value":"quiere","negate":false},{"value":"ser","negate":false},{"value":"mujer","negate":false},{"value":"la","negate":false},{"value":"tronera","negate":false},{"value":"por","negate":false},{"value":"antonio","negate":false},{"value":"gala","negate":false},{"value":"conjeturas","negate":false},{"value":"por","negate":false},{"value":"erasmo","negate":false},{"value":"todos","negate":false},{"value":"los","negate":false},{"value":"columnistas","negate":false},{"value":"»","negate":false},{"value":"15","negate":false},{"value":"08","negate":false},{"value":"2009","negate":false},{"value":"20","negate":false},{"value":"06","negate":false},{"value":"hrs","negate":false},{"value":"el","negate":false},{"value":"blog","negate":false},{"value":"de","negate":false},{"value":"santiago","negate":false},{"value":"gonz�lez","negate":false},{"value":"de","negate":false},{"value":"15","negate":false},{"value":"08","negate":false},{"value":"2009","negate":false},{"value":"18","negate":false},{"value":"01","negate":false},{"value":"hrs","negate":false},{"value":"el","negate":false},{"value":"mundo","negate":false},{"value":"por","negate":false},{"value":"dentro","negate":false},{"value":"de","negate":false},{"value":"10","negate":false},{"value":"08","negate":false},{"value":"2009","negate":false},{"value":"12","negate":false},{"value":"53","negate":false},{"value":"hrs","negate":false},{"value":"consejo","negate":false},{"value":"editorial","negate":false},{"value":"de","negate":false},{"value":"31","negate":false},{"value":"07","negate":false},{"value":"2009","negate":false},{"value":"13","negate":false},{"value":"06","negate":false},{"value":"hrs","negate":false},{"value":"dragolandia","negate":false},{"value":"de","negate":false},{"value":"30","negate":false},{"value":"07","negate":false},{"value":"2009","negate":false},{"value":"14","negate":false},{"value":"06","negate":false},{"value":"hrs","negate":false},{"value":"palabras","negate":false},{"value":"archivadas","negate":false},{"value":"de","negate":false},{"value":"�cree","negate":false},{"value":"que","negate":false},{"value":"eta","negate":false},{"value":"habr�","negate":false},{"value":"desaparecido","negate":false},{"value":"dentro","negate":false},{"value":"de","negate":false},{"value":"otros","negate":false},{"value":"50","negate":false},{"value":"a�os?","negate":false},{"value":"envía","negate":false},{"value":"tu","negate":false},{"value":"carta","negate":false},{"value":"ampliar","negate":false},{"value":"foto","negate":false},{"value":"09","negate":false},{"value":"07","negate":false},{"value":"2009","negate":false},{"value":"06","negate":false},{"value":"07","negate":false},{"value":"2009","negate":false},{"value":"03","negate":false},{"value":"07","negate":false},{"value":"2009","negate":false},{"value":"15","negate":false},{"value":"06","negate":false},{"value":"2009","negate":false},{"value":"devoto","negate":false},{"value":"de","negate":false},{"value":"al","negate":false},{"value":"qaeda","negate":false},{"value":"en","negate":false},{"value":"gaza","negate":false},{"value":"ampli�","negate":false},{"value":"el","negate":false},{"value":"guggenheim","negate":false},{"value":"de","negate":false},{"value":"nueva","negate":false},{"value":"york","negate":false}],"words":["líder","tiempo","sol","ataque","suicida","deficiencias","accidente","sufrimiento","desaparecido","ampliar","devoto"],"positive":["líder","sol","ampliar","devoto"],"negative":["tiempo","ataque","suicida","deficiencias","accidente","sufrimiento","desaparecido"]}}