{"page":0,"full_page":false,"headline":"\nDe vez en cuando la Justicia acelera\n","date":"2017-09-17T14:20:12.797Z","content":"\nDe vez en cuando la Justicia acelera\n\n\nProduce indignaci�n comprobar hasta d�nde ha llegado la desfachatez del independentismo y sus palmeros para intentar convencer al mundo de sus ilusorias aspiraciones ilegales para convocar un refer�ndum y, en caso de ganarlo, imponer unilateralmente la Rep�blica de Catalu�a.\nFundador y director de la fundaci�n Renacimiento Demogr�fico, Alejandro Macarr�n es ingeniero de telecomunicaciones, consultor empresarial y autor del libro Suicidio demogr�fico enOccidente y medio mundo, que pronto se publicar� en ingl�s.\n\n\nEl Mundo por dentro\n\n\n\n\nEl blog de Santiago Gonz�lez\n\n\n\n\nDragolandia\n\n\n\n\nFuera de l�nea\n\n\n\n\nBajos Fondos\n\n\nCargando siguiente contenido\n\n© ELMUNDO.es Avenida de San Luis 25 - 28033 MADRID Una web de Unidad Editorial\nSíguenos en","url":"https://www.elmundo.es/elmundo/hemeroteca/2017/09/17/m/opinion.html?intcmp=MENUHOM24801&s_kw=opinion","newspaper":"elmundo","scraper_id":"all-digitalocean-scraper","id":"c865162a-c568-4c85-649c-99ddbb3abe68","sentiment_analysis":{"score":-2,"comparative":-0.02,"tokens":[{"value":"de","negate":false},{"value":"vez","negate":false},{"value":"en","negate":false},{"value":"cuando","negate":false},{"value":"la","negate":false},{"value":"justicia","negate":false},{"value":"acelera","negate":false},{"value":"produce","negate":false},{"value":"indignaci�n","negate":false},{"value":"comprobar","negate":false},{"value":"hasta","negate":false},{"value":"d�nde","negate":false},{"value":"ha","negate":false},{"value":"llegado","negate":false},{"value":"la","negate":false},{"value":"desfachatez","negate":false},{"value":"del","negate":false},{"value":"independentismo","negate":false},{"value":"y","negate":false},{"value":"sus","negate":false},{"value":"palmeros","negate":false},{"value":"para","negate":false},{"value":"intentar","negate":false},{"value":"convencer","negate":false},{"value":"al","negate":false},{"value":"mundo","negate":false},{"value":"de","negate":false},{"value":"sus","negate":false},{"value":"ilusorias","negate":false},{"value":"aspiraciones","negate":false},{"value":"ilegales","negate":false},{"value":"para","negate":false},{"value":"convocar","negate":false},{"value":"un","negate":false},{"value":"refer�ndum","negate":false},{"value":"y","negate":false},{"value":"en","negate":false},{"value":"caso","negate":false},{"value":"de","negate":false},{"value":"ganarlo","negate":false},{"value":"imponer","negate":false},{"value":"unilateralmente","negate":false},{"value":"la","negate":false},{"value":"rep�blica","negate":false},{"value":"de","negate":false},{"value":"catalu�a","negate":false},{"value":"fundador","negate":false},{"value":"y","negate":false},{"value":"director","negate":false},{"value":"de","negate":false},{"value":"la","negate":false},{"value":"fundaci�n","negate":false},{"value":"renacimiento","negate":false},{"value":"demogr�fico","negate":false},{"value":"alejandro","negate":false},{"value":"macarr�n","negate":false},{"value":"es","negate":false},{"value":"ingeniero","negate":false},{"value":"de","negate":false},{"value":"telecomunicaciones","negate":false},{"value":"consultor","negate":false},{"value":"empresarial","negate":false},{"value":"y","negate":false},{"value":"autor","negate":false},{"value":"del","negate":false},{"value":"libro","negate":false},{"value":"suicidio","negate":false},{"value":"demogr�fico","negate":false},{"value":"enoccidente","negate":false},{"value":"y","negate":false},{"value":"medio","negate":false},{"value":"mundo","negate":false},{"value":"que","negate":false},{"value":"pronto","negate":false},{"value":"se","negate":false},{"value":"publicar�","negate":false},{"value":"en","negate":false},{"value":"ingl�s","negate":false},{"value":"el","negate":false},{"value":"mundo","negate":false},{"value":"por","negate":false},{"value":"dentro","negate":false},{"value":"el","negate":false},{"value":"blog","negate":false},{"value":"de","negate":false},{"value":"santiago","negate":false},{"value":"gonz�lez","negate":false},{"value":"dragolandia","negate":false},{"value":"fuera","negate":false},{"value":"de","negate":false},{"value":"l�nea","negate":false},{"value":"bajos","negate":false},{"value":"fondos","negate":false},{"value":"cargando","negate":false},{"value":"siguiente","negate":false},{"value":"contenido","negate":false},{"value":"©","negate":false},{"value":"elmundo","negate":false},{"value":"es","negate":false},{"value":"avenida","negate":false},{"value":"de","negate":false},{"value":"san","negate":false},{"value":"luis","negate":false},{"value":"25","negate":false},{"value":"-","negate":false},{"value":"28033","negate":false},{"value":"madrid","negate":false},{"value":"una","negate":false},{"value":"web","negate":false},{"value":"de","negate":false},{"value":"unidad","negate":false},{"value":"editorial","negate":false},{"value":"síguenos","negate":false},{"value":"en","negate":false}],"words":["justicia","convencer","imponer","autor","suicidio"],"positive":["justicia","convencer"],"negative":["imponer","autor","suicidio"]}}